litestar_oracledb/__init__.py
litestar_oracledb/__metadata__.py
litestar_oracledb/_utils.py
litestar_oracledb/exceptions.py
litestar_oracledb/plugin.py
litestar_oracledb/py.typed
litestar_oracledb/config/__init__.py
litestar_oracledb/config/_asyncio.py
litestar_oracledb/config/_common.py
litestar_oracledb/config/_sync.py
litestar_oracledb-0.2.0.dist-info/METADATA
litestar_oracledb-0.2.0.dist-info/WHEEL
litestar_oracledb-0.2.0.dist-info/licenses/LICENSE
litestar_oracledb-0.2.0.dist-info/RECORD
