Metadata-Version: 2.3
Name: litestar-oracledb
Version: 0.2.0
Summary: Oracle DB plugin for Litestar
Project-URL: Changelog, https://litestar-org.github.io/litesatr-oracledb/latest/changelog
Project-URL: Discord, https://discord.gg/X3FJqy8d2j
Project-URL: Documentation, https://litestar-org.github.io/litesatr-oracledb/latest/
Project-URL: Homepage, https://litestar-org.github.io/litesatr-oracledb/latest/
Project-URL: Issue, https://github.com/litestar-org/litestar-oracledb/issues/
Project-URL: Source, https://github.com/litestar-org/litestar-oracledb
Author-email: Cody Fincher <cody@litestar.dev>
License: MIT
License-File: LICENSE
Keywords: litestar,oracle
Classifier: Development Status :: 3 - Alpha
Classifier: Environment :: Web Environment
Classifier: Intended Audience :: Developers
Classifier: Intended Audience :: System Administrators
Classifier: License :: OSI Approved :: MIT License
Classifier: Natural Language :: English
Classifier: Operating System :: OS Independent
Classifier: Programming Language :: Python
Classifier: Programming Language :: Python :: 3.8
Classifier: Programming Language :: Python :: 3.9
Classifier: Programming Language :: Python :: 3.10
Classifier: Programming Language :: Python :: 3.11
Classifier: Programming Language :: Python :: 3.12
Classifier: Topic :: Database
Classifier: Topic :: Database :: Database Engines/Servers
Classifier: Topic :: Software Development
Classifier: Typing :: Typed
Requires-Python: >=3.8
Requires-Dist: litestar>=2.0.29
Requires-Dist: oracledb>2.1
